AUTHORS.rst
CONTRIBUTING.rst
HISTORY.rst
LICENSE
MANIFEST.in
README.rst
setup.cfg
setup.py
docs/Makefile
docs/authors.rst
docs/conf.py
docs/contributing.rst
docs/history.rst
docs/index.rst
docs/installation.rst
docs/make.bat
docs/readme.rst
docs/usage.rst
predex/__init__.py
predex/annoGenerator.py
predex/cli.py
predex/createComparisons.py
predex/designMatrix.py
predex/processIPAresults.py
predex.egg-info/PKG-INFO
predex.egg-info/SOURCES.txt
predex.egg-info/dependency_links.txt
predex.egg-info/entry_points.txt
predex.egg-info/not-zip-safe
predex.egg-info/requires.txt
predex.egg-info/top_level.txt
tests/__init__.py
tests/test_predex.py