Metadata-Version: 1.2
Name: predex
Version: 0.9.3
Summary: Prepare expression data for dgeAnalysis - LUMC.
Home-page: https://github.com/tomkuipers1402/predex
Author: Tom Kuipers
Author-email: t.b.kuipers@lumc.nl
License: MIT license
Keywords: predex
Platform: UNKNOWN
Classifier: Development Status :: 2 - Pre-Alpha
Classifier: Intended Audience :: Developers
Classifier: License :: OSI Approved :: MIT License
Classifier: Natural Language :: English
Classifier: Programming Language :: Python :: 3
Classifier: Programming Language :: Python :: 3.5
Classifier: Programming Language :: Python :: 3.6
Classifier: Programming Language :: Python :: 3.7
Classifier: Programming Language :: Python :: 3.8
Requires-Python: >3
